northstar/__init__.py
northstar/northstar.cpython-311-darwin.so
northstar_data-0.1.1.dist-info/LICENSE
northstar_data-0.1.1.dist-info/METADATA
northstar_data-0.1.1.dist-info/WHEEL
northstar_data-0.1.1.dist-info/top_level.txt
northstar_data-0.1.1.dist-info/RECORD
