Metadata-Version: 2.1
Name: northstar-data
Version: 0.1.1
Summary: A blazingly fast data processing library implemented in Rust with Python bindings
Home-page: https://github.com/marpit19/NorthStar
Author: Arpit Mohapatra
Author-email: arpit.mohapatra19@gmail.com
Classifier: Development Status :: 3 - Alpha
Classifier: Intended Audience :: Developers
Classifier: License :: OSI Approved :: MIT License
Classifier: Programming Language :: Python :: 3
Classifier: Programming Language :: Python :: 3.7
Classifier: Programming Language :: Python :: 3.8
Classifier: Programming Language :: Python :: 3.9
Classifier: Programming Language :: Rust
Requires-Python: >=3.7
License-File: LICENSE
